bookend/__init__.py
bookend/__main__.py
bookend/book.py
bookend/bookencoder.py
bookend/index.py
bookend/version.py
bookend/data/logger.ini
bookend-0.0.7.data/scripts/bookend
bookend-0.0.7.dist-info/LICENSE
bookend-0.0.7.dist-info/METADATA
bookend-0.0.7.dist-info/WHEEL
bookend-0.0.7.dist-info/entry_points.txt
bookend-0.0.7.dist-info/top_level.txt
bookend-0.0.7.dist-info/RECORD
